app_settings/__init__.py
app_settings/app_settings.py
app_settings-1.4.4.dist-info/LICENSE.md
app_settings-1.4.4.dist-info/METADATA
app_settings-1.4.4.dist-info/WHEEL
app_settings-1.4.4.dist-info/top_level.txt
app_settings-1.4.4.dist-info/RECORD
