Metadata-Version: 2.1
Name: app-settings
Version: 1.4.4
Summary: YAML for application configuration, lite version (inspired by Ruby gem "config")
Home-page: https://github.com/ivdunin/app_settings
Author: Ilya Dunin
Author-email: ilya.mirea@gmail.com
License: MIT
Platform: UNKNOWN
Classifier: Programming Language :: Python :: 3 :: Only
Classifier: License :: OSI Approved :: MIT License
Classifier: Operating System :: POSIX :: Linux
Classifier: Topic :: Software Development
Classifier: Topic :: Software Development :: Libraries :: Python Modules
Requires-Python: >=3.6
Requires-Dist: PyYAML (>=5.4)
